flask_lpackages/__init__.py
Flask_LPackages-1.0.0.dist-info/METADATA
Flask_LPackages-1.0.0.dist-info/WHEEL
Flask_LPackages-1.0.0.dist-info/top_level.txt
Flask_LPackages-1.0.0.dist-info/RECORD
