Metadata-Version: 2.1
Name: Flask-LPackages
Version: 1.0.0
Summary: Packages I need in my flask app
Author: Alexandr246
Author-email: alexandr246@vk.com
Keywords: packages list l flask app
Classifier: Programming Language :: Python :: 3.9
Classifier: License :: OSI Approved :: MIT License
Classifier: Operating System :: OS Independent
Requires-Python: >=3.9
Requires-Dist: Flask ==3.0.3
Requires-Dist: Flask-Login ==0.6.3
Requires-Dist: Flask-SQLAlchemy ==3.1.1
Requires-Dist: Flask-Migrate ==4.0.7
Requires-Dist: Flask-WTF ==1.2.1
Requires-Dist: python-dotenv ==1.0.1
Requires-Dist: Werkzeug ==3.0.4
